siteajax/__init__.py
siteajax/apps.py
siteajax/decorators.py
siteajax/middleware.py
siteajax/toolbox.py
siteajax/utils.py
siteajax/templates/siteajax/cdn.html
siteajax/templates/siteajax/init_csrf.js
siteajax/tests/__init__.py
siteajax/tests/conftest.py
siteajax/tests/test_basic.py
siteajax/tests/test_extensions.py
siteajax/tests/test_templates.py
siteajax/tests/testapp/__init__.py
siteajax/tests/testapp/urls.py
siteajax/tests/testapp/views.py
siteajax/tests/testapp/templates/index.html
django_siteajax-1.0.0.dist-info/AUTHORS
django_siteajax-1.0.0.dist-info/LICENSE
django_siteajax-1.0.0.dist-info/METADATA
django_siteajax-1.0.0.dist-info/WHEEL
django_siteajax-1.0.0.dist-info/top_level.txt
django_siteajax-1.0.0.dist-info/RECORD
